bleat/__init__.py
bleat/main.py
bleat-0.0.1.dist-info/METADATA
bleat-0.0.1.dist-info/WHEEL
bleat-0.0.1.dist-info/top_level.txt
bleat-0.0.1.dist-info/RECORD
